my_mini_package/__init__.py
my_mini_package/single_function.py
my_mini_package-0.1.0.dist-info/METADATA
my_mini_package-0.1.0.dist-info/WHEEL
my_mini_package-0.1.0.dist-info/top_level.txt
my_mini_package-0.1.0.dist-info/RECORD
