Metadata-Version: 2.2
Name: my-mini-package
Version: 0.1.0
Summary: A minimal package with one function to learn PyPI uploads.
Author-email: Your Name <you@example.com>
License: MIT
Project-URL: Homepage, https://github.com/ExampleUserName/my-mini-package
Keywords: example,learning,packaging
Classifier: Programming Language :: Python :: 3
Classifier: License :: OSI Approved :: MIT License
Classifier: Operating System :: OS Independent
Requires-Python: >=3.8
